specgp/__init__.py
specgp/distributions.py
specgp/means.py
specgp/terms.py
specgp-0.2.dist-info/METADATA
specgp-0.2.dist-info/WHEEL
specgp-0.2.dist-info/top_level.txt
specgp-0.2.dist-info/RECORD
