Metadata-Version: 2.1
Name: specgp
Version: 0.2
Summary: Gaussian processes for multi-wavelength and spectral observations
Home-page: http://github.com/tagordon/specgp
Author: Tyler Gordon
Author-email: tagordon@uw.edu
License: MIT
Platform: UNKNOWN
Requires-Dist: numpy
Requires-Dist: scipy
Requires-Dist: exoplanet
Requires-Dist: pymc3
Requires-Dist: theano
